<?xml version="1.0" encoding="utf-8"?>
<translations>
   <translation id="button_renew" qtlid="210124">Uusinta</translation>
   <translation id="cdnwebstorage_dashboard_loading_error" qtlid="168120">Tapahtui virhe ladattaessa tietoja.</translation>
   <translation id="cdnwebstorage_dashboard_loading_expire" qtlid="148461">Palvelu on vanhentunut</translation>
   <translation id="cdnwebstorage_dashboard_storage_use" qtlid="168146">Levytila</translation>
   <translation id="cdnwebstorage_dashboard_turnover" qtlid="145215">Tallennustilan uudistaminen</translation>
   <translation id="cdnwebstorage_dashboard_dead_date" qtlid="145228">Liikennöinnin loppumisen ennustettu päivämäärä</translation>
   <translation id="cdnwebstorage_configuration_access_webapp_title_button" qtlid="145241">Pääsy WebAppiin</translation>
   <translation id="cdnwebstorage_configuration_order_storage_title" qtlid="145254">Tilaa tallennustila</translation>
   <translation id="cdnwebstorage_configuration_order_traffic_title" qtlid="145267">Tilaa liikennöintiä</translation>
   <translation id="cdnwebstorage_configuration_more_than_free_month" qtlid="129507">+3 kuukautta</translation>
   <translation id="cdnwebstorage_configuration_storage_use_unavailable" qtlid="145280">Graafi ei saatavilla</translation>
   <translation id="cdnwebstorage_tab_traffic" qtlid="39202">Liikenne</translation>
   <translation id="cdnwebstorage_tab_traffic_type" qtlid="105875">Tyyppi:</translation>
   <translation id="cdnwebstorage_tab_traffic_type_QUOTA" qtlid="153571">Quota (jäljellä oleva liikenne)</translation>
   <translation id="cdnwebstorage_tab_traffic_type_TRAFFIC" qtlid="153545">Ulos menevä kulutettu liikenne</translation>
   <translation id="cdnwebstorage_tab_traffic_from" qtlid="145293">Aikaväli:</translation>
   <translation id="cdnwebstorage_tab_traffic_from_DAY" qtlid="126844">Viimeiset 24 tuntia</translation>
   <translation id="cdnwebstorage_tab_traffic_from_MONTH" qtlid="99632">30 päivää</translation>
   <translation id="cdnwebstorage_tab_traffic_from_WEEK" qtlid="126856">Viimeiset 7 päivää</translation>
   <translation id="cdnwebstorage_tab_traffic_legend_TRAFFIC" qtlid="127770">CDN-välimuistista</translation>
   <translation id="cdnwebstorage_tab_traffic_legend_backend" qtlid="127782">Webhotellista</translation>
   <translation id="cdnwebstorage_tab_traffic_legend_QUOTA" qtlid="143186">Jäljellä oleva liikenne</translation>
   <translation id="cdnwebstorage_tab_traffic_legend_y_QUOTA" qtlid="226826">Gio jäljellä</translation>
   <translation id="cdnwebstorage_tab_traffic_legend_y_TRAFFIC" qtlid="153545">Ulos menevä kulutettu liikenne</translation>
   <translation id="cdnwebstorage_order_totalHT" qtlid="169238">Hinta (ALV 0 %)</translation>
   <translation id="cdnwebstorage_order_totalTTC" qtlid="169251">Hinta (ALV 24 %)</translation>
   <translation id="cdnwebstorage_order_traffic_step1_question" qtlid="145332">Valitse ulos menevä liikennöinti jonka haluat lisätä:</translation>
   <translation id="cdnwebstorage_order_traffic_step2_question" qtlid="145345">{0} liikennöintiä lisätään palvelimelle {1}</translation>
   <translation id="cdnwebstorage_order_traffic_step2_traffic" qtlid="145358">Liikennöinti:</translation>
   <translation id="cdnwebstorage_order_traffic_step2_confirm" qtlid="167873">Vahvistaaksesi pyyntösi, klikkaa alla olevaa ”Tilaus”-nappia.</translation>
   <translation id="cdnwebstorage_order_traffic_step2_explication" qtlid="167886">Uusi välilehti avataan ja sinut ohjataan OVH:n maksusivulle.</translation>
   <translation id="cdnwebstorage_order_traffic_step2_contracts" qtlid="145371">Vahvistan, että olen lukenut ja ymmärtänyt seuraavat ehdot:</translation>
   <translation id="cdnwebstorage_order_traffic_finish_success" qtlid="145384">Liikennöintitilaus on tehty onnistuneesti.</translation>
   <translation id="cdnwebstorage_order_traffic_finish_fail" qtlid="145397">Tapahtui virhe tilattaessa lisää liikennöintiä palvelimelle {0}</translation>
   <translation id="cdnwebstorage_order_storage_step1_question" qtlid="145462">Valitse tallennustila, johon haluat päivittää:</translation>
   <translation id="cdnwebstorage_order_storage_step1_warning" qtlid="145475">Huomio: et voi alentaa CDN Webstorage -levytilaasi - vain päivitys on mahdollinen.</translation>
   <translation id="cdnwebstorage_order_storage_step1_not_available" qtlid="145488">päivitys pienempään pakettiin ei ole mahdollinen</translation>
   <translation id="cdnwebstorage_order_storage_step2_question" qtlid="145501">CDN Webstoragen {0} päivitys levytilaan {1}</translation>
   <translation id="cdnwebstorage_order_storage_step2_question2" qtlid="169784">Hinta seuraavaan palvelimesi vanhentumispäivämäärään, {0} asti</translation>
   <translation id="cdnwebstorage_order_storage_step2_confirm" qtlid="167873">Vahvistaaksesi pyyntösi, klikkaa alla olevaa ”Tilaus”-nappia.</translation>
   <translation id="cdnwebstorage_order_storage_step2_explication" qtlid="167886">Uusi välilehti avataan ja sinut ohjataan OVH:n maksusivulle.</translation>
   <translation id="cdnwebstorage_order_storage_step2_contracts" qtlid="145371">Vahvistan, että olen lukenut ja ymmärtänyt seuraavat ehdot:</translation>
   <translation id="cdnwebstorage_order_storage_finish_success" qtlid="145514">Tallennustilan päivitys -tilaus on tehty onnistuneesti.</translation>
   <translation id="cdnwebstorage_order_storage_finish_fail" qtlid="145527">Tapahtui virhe tilattaessa tallennustilan päivitystä palvelimelle {0}</translation>
</translations>
