<?xml version="1.0" encoding="utf-8"?>
<translations>
   <translation id="domain_email_obfuscation_back_button" qtlid="522565">Ersatz-E-Mails neu generieren</translation>
   <translation id="domain_email_obfuscation_label" qtlid="522578">Wählen Sie die Kontakte aus, für die Sie die Ersatz-E-Mails neu generieren möchten:</translation>
   <translation id="domain_email_obfuscation_regenerate" qtlid="69797">Änderungen speichern</translation>
   <translation id="domain_email_obfuscation_contact_admin" qtlid="259159">Administrator-Kontakt</translation>
   <translation id="domain_email_obfuscation_contact_owner" qtlid="522591">Inhaber-Kontakt</translation>
   <translation id="domain_email_obfuscation_contact_tech" qtlid="16541">Techkontakt</translation>
   <translation id="domain_email_obfuscation_active" qtlid="522604">Verschleiern</translation>
   <translation id="domain_email_obfuscation_inactive" qtlid="522617">Offene Anzeige</translation>
   <translation id="domain_email_obfuscation_mail">l'adresse e-mail personnelle du contact</translation>
   <translation id="domain_email_obfuscation_refresh" qtlid="522643">Verschleierungs-E-Mail neu generieren</translation>
   <translation id="domain_email_obfuscation_refresh_success" qtlid="522656">Die E-Mail-Adressen wurden neu generiert.</translation>
   <translation id="domain_email_obfuscation_refresh_error" qtlid="522669">Bei der Neugenerierung Ihrer E-Mail-Adressen ist ein Fehler aufgetreten: {{ message }}</translation>
   <translation id="domain_email_obfuscation_error" qtlid="168120">Beim Laden der Informationen ist ein Fehler aufgetreten.</translation>
</translations>
