<?xml version="1.0" encoding="utf-8"?>
<translations>
   <translation id="email_tab_GENERAL_INFORMATIONS" qtlid="27115">General information</translation>
   <translation id="email_dashboard_general_informations" qtlid="27115">General information</translation>
   <translation id="email_dashboard_quotas" qtlid="297202">Quotas</translation>
   <translation id="email_tab_EMAIL" qtlid="218029">Emails</translation>
   <translation id="email_tab_MAILING_LIST" qtlid="50182">Mailing-lists</translation>
   <translation id="email_tab_TASK" qtlid="344097">Ongoing tasks </translation>
   <translation id="email_tab_menu_resiliate" qtlid="370174">Delete/Cancel my MX Plan</translation>
   <translation id="emails_common_from" qtlid="69077">From</translation>
   <translation id="emails_common_to" qtlid="175972">To</translation>
   <translation id="emails_common_date_from" qtlid="88725">From</translation>
   <translation id="emails_common_date_to" qtlid="88737">To</translation>
   <translation id="emails_common_copy_to" qtlid="218055">Copy to</translation>
   <translation id="emails_common_continue_question" qtlid="351844">Do you want to continue?</translation>
   <translation id="emails_common_status" qtlid="33790">Status</translation>
   <translation id="emails_common_required_fields" qtlid="222111">The fields marked with a star are mandatory</translation>
   <translation id="emails_common_new_window" qtlid="222176">New window</translation>

   <translation id="email_tab_table_no_quota" qtlid="228196">You cannot create an email account. </translation>
   <translation id="email_tab_table_emails_quota_excedeed" qtlid="223424">You cannot create an email account. </translation>
   <translation id="email_tab_table_emails_quota_excedeed_1" qtlid="223437">You can no longer create an email account. 1 email account out of 1 available account has been set up.</translation>
   <translation id="email_tab_table_emails_quota_excedeed_other" qtlid="223450">You can no longer create an email account. {0} email accounts out of {1} available accounts have been set up.</translation>
   <translation id="email_tab_table_emails_responder_quota_excedeed" qtlid="221188">You can no longer set up an auto-response. {0} auto-responses out of the {1} available have been configured.</translation>
   <translation id="email_tab_table_header_account_name" qtlid="9202">Account Name</translation>
   <translation id="email_tab_table_header_account_description" qtlid="9238">Description</translation>
   <translation id="email_tab_table_header_account_size" qtlid="7726">Size</translation>
   <translation id="email_tab_table_header_account_date" qtlid="191291">Last update</translation>
   <translation id="email_tab_table_header_account_bloqued" qtlid="221201">Blocked due to SPAM</translation>
   <translation id="email_tab_table_header_refresh" qtlid="218081">Reload the table</translation>
   <translation id="email_tab_table_header_filters" qtlid="2606">Filters</translation>
   <translation id="email_tab_table_header_redirections" qtlid="46204">Redirections</translation>
   <translation id="email_tab_table_header_responders" qtlid="218094">Auto-response</translation>
   <translation id="email_tab_table_emails_empty" qtlid="218107">No account</translation>
   <translation id="email_tab_button_emails_create_account" qtlid="21487">Add an account</translation>
   <translation id="email_tab_button_emails_create_account" qtlid="302054">Create an email address </translation>
   <translation id="email_tab_table_emails_block_false" qtlid="50602">no</translation>
   <translation id="email_tab_table_emails_block_true" qtlid="50134">yes</translation>
   <translation id="email_tab_table_emails_unlock" qtlid="221214">Click to unblock the account</translation>
   <translation id="email_tab_table_accounts_error" qtlid="218120">There was an error when recovering accounts: </translation>
   <translation id="email_tab_button_emails_export_CSV" qtlid="231773">Export in CSV</translation>

   <translation id="email_tab_modal_unlock_account_title" qtlid="221227">Unblock an account</translation>
   <translation id="email_tab_modal_unlock_account_heading" qtlid="221240">The <strong>{0}</strong> account is currently blocked.</translation>
   <translation id="email_tab_modal_unlock_account_infos" qtlid="221253">For it to function again, you must change your password.</translation>

   <translation id="email_tab_filters_management_heading" qtlid="218133">Account filter management</translation>
   <translation id="email_tab_table_header_filter_name" qtlid="218146">Filter name</translation>
   <translation id="email_tab_table_header_filter_priority" qtlid="45988">Priority</translation>
   <translation id="email_tab_table_header_filter_active" qtlid="55133">Active</translation>
   <translation id="email_tab_table_header_refresh" qtlid="218081">Reload the table</translation>
   <translation id="email_tab_table_filters_empty" qtlid="85281">No filter</translation>
   <translation id="email_tab_button_emails_create_filter" qtlid="85329">Add a filter</translation>
   <translation id="email_tab_button_emails_filters_back" qtlid="4118">Back</translation>
   <translation id="email_tab_filters_status_true" qtlid="65490">enabled</translation>
   <translation id="email_tab_filters_status_false" qtlid="65694">disabled</translation>
   <translation id="email_tab_table_filters_error" qtlid="218159">An error occurred when the filters were being recovered: </translation>

   <translation id="email_tab_modal_create_account_title" qtlid="218172">You are going to create a new email account</translation>
   <translation id="email_tab_modal_create_account_heading" qtlid="218185">Please enter the account details</translation>
   <translation id="email_tab_modal_create_account_account_name" qtlid="147464">Account name:</translation>
   <translation id="emails_common_account_name_conditions" qtlid="222787">Please note: the account name must respect the following criteria: <br/>- Minimum {0} characters<br/>- Maximum {1} characters<br/>- No space<br/>- No accented characters<br/>- No special characters apart from ., - and _.</translation>
   <translation id="emails_common_sub_domain_conditions" qtlid="323418">Please note, the sub-domain must meet the following criteria:<br/> - No space<br/>- No accents<br/>- No special characters apart from - and _.</translation>
   <translation id="emails_common_account_description_conditions" qtlid="228209">Please note that the account description must respect the following criteria: <br/>- Maximum {0} characters (this figure will be smaller when special characters or accents are included)<br/>- No ':'</translation>
   <translation id="emails_common_account_over_quota" qtlid="285082">If you are looking for more than 5GB of storage, please view <a href="{0}" target="_blank">our exchange offers</a>.</translation>
   <translation id="email_tab_modal_create_account_account_description" qtlid="218224">Account description:</translation>
   <translation id="email_tab_modal_create_account_account_size" qtlid="218237">Account size:</translation>
   <translation id="email_tab_modal_create_account_account_password" qtlid="91129">Password:</translation>
   <translation id="email_tab_modal_create_account_account_password_confirm" qtlid="197063">Confirmation:</translation>
   <translation id="email_tab_modal_create_account_account_password_error" qtlid="218250">Invalid password</translation>
   <translation id="email_tab_modal_create_account_account_password_match_error" qtlid="218263">The passwords do not match</translation>
   <translation id="email_tab_modal_create_account_account_validation_text" qtlid="285369">Confirmation of email account creation </translation>
   <translation id="email_tab_modal_create_account_success" qtlid="218276">Your email account is being created. It will be available in 5 to 10 minutes.</translation>
   <translation id="email_tab_modal_create_account_error" qtlid="218289">An error occurred when your account was being created:</translation>
   <translation id="email_tab_modal_create_account_devices_MAC" qtlid="402204">Mac</translation>
   <translation id="email_tab_modal_create_account_devices_OUTLOOK" qtlid="402217">Windows Outlook </translation>
   <translation id="email_tab_modal_create_account_devices_IPHONE" qtlid="402204">Mac</translation>
   <translation id="email_tab_modal_create_account_devices_ANDROID" qtlid="402204">Mac</translation>
   <translation id="email_tab_modal_create_account_devices_OTHER" qtlid="402204">Mac</translation>
   <translation id="email_tab_modal_create_account_guides_autoconfig" qtlid="273319">Automatic configuration </translation>


   <translation id="email_tab_error" qtlid="218302">An error occurred:</translation>
   <translation id="emails_common_password_conditions" qtlid="218315">Please note: the password must respect the following criteria: <br/>- Minimum {0} characters<br/>- Maximum {1} characters<br/>- No accented characters</translation>
   <translation id="email_tab_popover_import_from_imap" qtlid="218328">Import emails from another account</translation>
   <translation id="email_tab_popover_filters" qtlid="218341">Manage filters</translation>
   <translation id="email_tab_popover_update_account" qtlid="218354">Modify the account</translation>
   <translation id="email_tab_popover_change_password_account" qtlid="80394">Change the password</translation>
   <translation id="email_tab_popover_delete_account" qtlid="150294">Delete the account</translation>
   <translation id="email_tab_popover_delegate" qtlid="369732">Delegation management </translation>
   <translation id="email_tab_popover_migrate" qtlid="436619">Migrer le compte</translation>
   <translation id="email_tab_modal_change_password_title" qtlid="218367">Change the account password</translation>
   <translation id="email_tab_modal_change_password_heading" qtlid="218380">You are about to change your account password</translation>
   <translation id="email_tab_modal_change_account_password_success" qtlid="218393">Your password is being changed. The operation will take effect in 5 to 10 minutes.</translation>
   <translation id="email_tab_modal_change_account_password_error" qtlid="218406">An error occurred when your password was being changed:</translation>
   <translation id="email_tab_modal_delete_account_title" qtlid="218419">Delete an account</translation>
   <translation id="email_tab_modal_delete_account_heading" qtlid="218432">You are about to delete the <strong>{0}</strong> account</translation>
   <translation id="email_tab_modal_delete_account_warning" qtlid="212270">Please note that this action is not reversible and will result in the loss of all data.</translation>
   <translation id="email_tab_modal_delete_account_error" qtlid="218445">An error occurred when the account was being deleted:</translation>
   <translation id="email_tab_modal_delete_account_success" qtlid="218458">Your email account is being deleted. The operation will take effect in 5 to 10 minutes.</translation>
   <translation id="email_tab_modal_delete_account_error" qtlid="218445">An error occurred when the account was being deleted:</translation>
   <translation id="email_tab_modal_import_from_imap_title" qtlid="218471">Import emails</translation>
   <translation id="email_tab_modal_import_from_imap_heading" qtlid="218484">You are going to import emails from another account</translation>
   <translation id="email_tab_modal_import_from_imap_account_info" qtlid="363544">Please enter source account details </translation>
   <translation id="email_tab_modal_import_from_imap_server_addr" qtlid="218510">IMAP server address:</translation>
   <translation id="email_tab_modal_import_from_imap_use_ssh" qtlid="218523">Enable SSL</translation>
   <translation id="email_tab_modal_import_from_imap_account_password" qtlid="363557">Please enter the email account password </translation>
   <translation id="email_tab_modal_import_from_imap_success" qtlid="288132">Emails are being imported. The time it takes to complete this task will depend on the number of emails. </translation>
   <translation id="email_tab_modal_import_from_imap_error" qtlid="221292">An error occurred when the emails were being imported:</translation>

   <translation id="email_tab_modal_emails_update_account" qtlid="218354">Modify the account</translation>
   <translation id="email_tab_modal_update_account_title" qtlid="218549">You are going to modify the {0} account</translation>
   <translation id="email_tab_modal_update_account_heading" qtlid="218562">Please enter the following information:</translation>
   <translation id="email_tab_modal_update_account_success" qtlid="218575">Your email account is being modified. The operation will take effect in 5 to 10 minutes.</translation>
   <translation id="email_tab_modal_update_account_error" qtlid="218588">An error occurred when the account was being modified:</translation>

   <translation id="email_tab_modal_update_usage_title" qtlid="383564">Storage quota update</translation>
   <translation id="email_tab_modal_update_usage_success" qtlid="383577">We have registered your request to update your storage quota. This will be updated in 5 to 10 minutes.<br/>Please refresh the page once this time has elapsed.&#13;
</translation>
   <translation id="email_tab_modal_update_usage_error" qtlid="383590">There was an error when you asked for your storage quota to be updated. </translation>
   <translation id="email_tab_modal_update_usage_info" qtlid="383603">You are about to request that your account's storage quota be changed. Please note that you can only make one request every five minutes. </translation>
   <translation id="email_tab_modal_update_usage_lastupdate" qtlid="383616">Last update: {0}</translation>
   <translation id="email_tab_modal_update_usage_alert_updating" qtlid="383629">Careful, you have recently requested an update of your storage quota. </translation>

   <translation id="email_tab_popover_filter_create" qtlid="70613">Create a filter</translation>
   <translation id="email_tab_modal_filter_create_heading" qtlid="218601">You are going to set up a filter for the {0} account</translation>

   <translation id="email_tab_modal_filter_create_info" qtlid="218614">Please enter the information on the filter</translation>
   <translation id="email_tab_modal_filter_create_info_heading" qtlid="29227">Information</translation>
   <translation id="email_tab_modal_filter_create_rules_heading" qtlid="159813">Rules</translation>
   <translation id="email_tab_modal_filter_create_action_heading" qtlid="56105">Action</translation>
   <translation id="email_tab_modal_filter_create_name" qtlid="218627">Filter name:</translation>
   <translation id="email_tab_modal_filter_create_name_conditions" qtlid="228222">Please note that the filter name must not already exist, or include spaces, special or accented characters.</translation>
   <translation id="email_tab_modal_filter_create_header" qtlid="218640">Header</translation>
   <translation id="email_tab_modal_filter_create_header_From" qtlid="69077">From</translation>
   <translation id="email_tab_modal_filter_create_header_To" qtlid="69089">To</translation>
   <translation id="email_tab_modal_filter_create_header_Subject" qtlid="221955">Message subject</translation>
   <translation id="email_tab_modal_filter_create_header_Body" qtlid="221968">Message content</translation>
   <translation id="email_tab_modal_filter_create_header_other" qtlid="19963">Other</translation>
   <translation id="email_tab_modal_filter_create_action" qtlid="218653">Action:</translation>
   <translation id="email_tab_modal_filter_create_priority" qtlid="218666">Priority:</translation>
   <translation id="email_tab_modal_filter_create_active" qtlid="221981">Enable the filter</translation>
   <translation id="email_tab_modal_filter_create_rule" qtlid="54917">Rule</translation>
   <translation id="email_tab_modal_filter_create_value" qtlid="47548">Value</translation>
   <translation id="email_tab_modal_filter_create_rule_checkspf" qtlid="218679">spf</translation>
   <translation id="email_tab_modal_filter_create_rule_contains" qtlid="218692">includes</translation>
   <translation id="email_tab_modal_filter_create_rule_noContains" qtlid="218705">doesn't include</translation>
   <translation id="email_tab_modal_filter_create_action_accept" qtlid="218718">accept</translation>
   <translation id="email_tab_modal_filter_create_action_account" qtlid="221994">redirect to a local address</translation>
   <translation id="email_tab_modal_filter_create_action_bounce" qtlid="222007">return to the sender</translation>
   <translation id="email_tab_modal_filter_create_action_delete" qtlid="218757">deletion</translation>
   <translation id="email_tab_modal_filter_create_action_redirect" qtlid="222020">redirect to a remote address</translation>
   <translation id="email_tab_modal_filter_create_actionParam" qtlid="218783">Action settings:</translation>
   <translation id="email_tab_modal_filter_create_actionParam_account" qtlid="222033">Local account:</translation>
   <translation id="email_tab_modal_filter_create_actionParam_redirect" qtlid="222046">Remote address:</translation>
   <translation id="email_tab_modal_create_filter_success" qtlid="218796">The filter is being set up. It will be available in 5 to 10 minutes.</translation>
   <translation id="email_tab_modal_create_filter_error" qtlid="218809">An error occurred when the filter was being set up.</translation>
   <translation id="email_tab_modal_create_filter_number_error" qtlid="218822">You must select a numerical value.</translation>

   <translation id="email_tab_modal_create_filter_help_title" qtlid="218835">Configure a filter</translation>
   <translation id="email_tab_modal_create_filter_help_priority_title" qtlid="45988">Priority</translation>
   <translation id="email_tab_modal_create_filter_help_priority_desc" qtlid="218848">Select the filter's priority level. The smaller the value, the more important the filter.</translation>
   <translation id="email_tab_modal_create_filter_help_rule_title" qtlid="54917">Rule</translation>
   <translation id="email_tab_modal_create_filter_help_rule_desc" qtlid="218861">The rules define the parameters on which the filter organises information. They are made up of a header, an operand and a value. The most common headings are: <ul><li><strong>From</strong>: The sender</li><li><strong>To</strong>: The recipient</li><li><strong>Subject</strong>: The subject</li></ul></translation>

   <translation id="email_tab_modal_delete_filter_title" qtlid="218874">Delete a filter</translation>
   <translation id="email_tab_modal_delete_filter_heading" qtlid="218887">You are going to delete the {0} filter.</translation>
   <translation id="email_tab_modal_delete_filter_success" qtlid="218900">The filter is being deleted. The operation will take effect in 5 to 10 minutes.</translation>
   <translation id="email_tab_modal_delete_filter_error" qtlid="218913">An error occurred when the filter was being deleted.</translation>

   <translation id="email_tab_popover_filter_edit" qtlid="221305">Modify the filter</translation>
   <translation id="email_tab_popover_filter_delete" qtlid="218939">Delete the filter</translation>

   <translation id="email_tab_modal_edit_filter_title" qtlid="218952">Modify a filter</translation>
   <translation id="email_tab_modal_edit_filter_heading" qtlid="218965">You are going to modify the {0} filter</translation>
   <translation id="email_tab_modal_filter_edit_info" qtlid="218614">Please enter the information on the filter</translation>
   <translation id="email_tab_modal_edit_filter_success" qtlid="218978">The filter is being modified. The operation will take effect in 5 to 10 minutes.</translation>
   <translation id="email_tab_modal_edit_filter_error" qtlid="218991">An error occurred when the filter was being modified.</translation>
   <translation id="email_tab_export_accounts_csv_title" qtlid="217015">Exporting accounts in CSV</translation>
   <translation id="email_tab_access_webmail" qtlid="222800">Go to the Webmail</translation>

   <translation id="email_tab_modal_export_csv_title" qtlid="217015">Exporting accounts in CSV</translation>
   <translation id="emails_export_csv_expl" qtlid="251837">It can take up to a few minutes to export your email accounts, depending on the number of accounts you have.</translation>
   <translation id="emails_export_csv_confirm" qtlid="217080">Are you sure that you want to export your accounts?</translation>
   <translation id="emails_export_csv_doing" qtlid="251850">Exporting...</translation>
   <translation id="email_tab_modal_accounts_export_csv_success" qtlid="374971">The file has been created. If the download doesn't start automatically, you can <a target="_blank" href="{0}">download it manually</a>.</translation>
   <translation id="email_tab_modal_accounts_export_csv_error" qtlid="251876">An error occurred when exporting your accounts to a CSV file.</translation>


   <translation id="email_tab_redirections_management_title" qtlid="98948">Manage redirections</translation>
   <translation id="email_tab_redirections_management_heading" qtlid="219004">Manage account redirections</translation>
   <translation id="email_tab_button_emails_create_redirection" qtlid="213713">Add a redirection</translation>
   <translation id="email_tab_table_redirections_empty" qtlid="219017">No redirection</translation>
   <translation id="email_tab_redirections_management_heading" qtlid="219004">Manage account redirections</translation>
   <translation id="email_tab_modal_create_redirection_title" qtlid="219030">Create a redirection</translation>
   <translation id="email_tab_modal_create_redirection_heading" qtlid="219043">You are going to create a redirection for the {0} account</translation>
   <translation id="email_tab_modal_create_redirection_type" qtlid="220304">Redirection type:</translation>
   <translation id="email_tab_modal_create_redirection_type_classic" qtlid="221318">Standard redirection</translation>
   <translation id="email_tab_modal_create_redirection_type_sub_domain" qtlid="221331">Redirect a sub-domain</translation>
   <translation id="email_tab_modal_redirection_create_from" qtlid="219056">From the address:</translation>
   <translation id="email_tab_modal_redirection_create_subdomain_optional" qtlid="272825">sub-domain (optional)</translation>
   <translation id="email_tab_modal_redirection_create_to" qtlid="219069">To the address:</translation>
   <translation id="email_tab_modal_create_redirection_info" qtlid="219082">Please enter the redirection information</translation>
   <translation id="email_tab_modal_redirection_create_keep_copy_title" qtlid="302067">Choose a copy method: </translation>
   <translation id="email_tab_modal_redirection_create_email_error" qtlid="212036">Invalid email</translation>
   <translation id="email_tab_modal_redirection_create_copy_local" qtlid="302080">Keep a copy of the email at OVH </translation>
   <translation id="email_tab_modal_redirection_create_copy_none" qtlid="302093">Don't keep a copy of the email </translation>
   <translation id="email_tab_modal_redirection_create_copy_select" qtlid="302106">Please choose an option </translation>
   <translation id="email_tab_popover_redirection_delete" qtlid="219108">Delete the redirection</translation>
   <translation id="email_tab_modal_create_redirection_success" qtlid="262960">Email redirection is being created. This will take a few minutes.</translation>
   <translation id="email_tab_modal_create_redirection_error" qtlid="219134">An error occurred when the redirection was being set up:</translation>
   <translation id="email_tab_modal_delete_redirection_success" qtlid="262973">Email redirection is being deleted. This will take a few minutes.</translation>
   <translation id="email_tab_modal_delete_redirection_error" qtlid="213466">Error when deleting the redirection.</translation>
   <translation id="email_tab_table_redirections_error" qtlid="219160">An error occurred when the redirections were being retrieved:</translation>
   <translation id="email_tab_modal_delete_redirection_title" qtlid="221344">Delete a redirection</translation>
   <translation id="email_tab_modal_delete_redirection_heading" qtlid="221357">You are going to delete a redirection:</translation>
   <translation id="email_tab_modal_delete_redirection_accounts" qtlid="221370"><strong>{0}</strong> to <strong>{1}</strong></translation>
   <translation id="email_tab_popover_redirection_update" qtlid="99224">Modify redirections</translation>

   <translation id="email_tab_responders_message_warning" qtlid="363570">Please note: only Latin characters work for the auto-response. </translation>
   <translation id="email_tab_responders_management_heading" qtlid="221383">Manage auto-responses</translation>
   <translation id="email_tab_responders_status_expired_true" qtlid="58676">Expired</translation>
   <translation id="email_tab_responders_status_expired_false" qtlid="55133">Active</translation>
   <translation id="email_tab_responders_name" qtlid="3818">Name</translation>
   <translation id="email_tab_table_responders_empty" qtlid="221396">No auto-response</translation>
   <translation id="email_tab_modal_create_responder_title" qtlid="221409">Add an auto-response</translation>
   <translation id="email_tab_modal_create_responder_heading" qtlid="221422">You are going to create an auto-response</translation>
   <translation id="email_tab_modal_create_responder_info" qtlid="221435">Please enter the auto-response information</translation>
   <translation id="email_tab_table_responders_error" qtlid="219251">An error occurred when the responses were being retrieved:</translation>

   <translation id="email_tab_modal_create_responder_type" qtlid="220460">Auto-response type:</translation>
   <translation id="email_tab_modal_create_responder_type_attached" qtlid="221448">Add an email address</translation>
   <translation id="email_tab_modal_create_responder_type_free" qtlid="221461">Free (no need for an existing mailbox)</translation>
   <translation id="email_tab_modal_create_responder_account" qtlid="221474">Mailbox:</translation>
   <translation id="email_tab_modal_create_responder_name" qtlid="221487">Auto-response name:</translation>
   <translation id="email_tab_modal_create_responder_start" qtlid="221500">From:</translation>
   <translation id="email_tab_modal_create_responder_end" qtlid="221513">Until:</translation>
   <translation id="email_tab_modal_create_responder_copy" qtlid="219277">Send a copy</translation>
   <translation id="email_tab_modal_create_responder_not_delete_message" qtlid="228397">Do not delete the message</translation>
   <translation id="email_tab_modal_create_responder_delete_message" qtlid="273384">Keep messages on the server</translation>
   <translation id="email_tab_modal_create_responder_copy_warning" qtlid="273397">All emails received during auto-response activation will be deleted. It will not be possible to recover them .</translation>
   <translation id="email_tab_modal_create_responder_copy_to" qtlid="221526">Copy address:</translation>
   <translation id="email_tab_modal_create_responder_duration" qtlid="221539">Duration of auto-response:</translation>
   <translation id="email_tab_modal_create_responder_permanent" qtlid="221552">permanent</translation>
   <translation id="email_tab_modal_create_responder_temporary" qtlid="221565">temporary</translation>
   <translation id="email_tab_modal_create_responder_exists" qtlid="221578">An auto-response with this name already exists.</translation>
   <translation id="email_tab_modal_create_account_exists" qtlid="228410">An account already exists with this name.</translation>
   <translation id="email_tab_modal_create_responder_message" qtlid="75606">Message:</translation>
   <translation id="email_tab_modal_create_responder_success" qtlid="221591">Your auto-response is being set up. It will be available in 5 to 10 minutes.</translation>
   <translation id="email_tab_modal_create_responder_error" qtlid="221604">An error occurred when the auto-response was being set up.</translation>
   <translation id="email_tab_modal_delete_responder_title" qtlid="221617">Delete an auto-response</translation>
   <translation id="email_tab_modal_delete_responder_heading" qtlid="220616">You are going to delete the auto-response {0}.</translation>
   <translation id="email_tab_modal_delete_responder_success" qtlid="221630">The auto-response is being deleted. The operation will take effect in 5 to 10 minutes.</translation>

   <translation id="email_tab_modal_delete_responder_error" qtlid="221643">An error occurred when the auto-response was being deleted.</translation>
   <translation id="email_tab_popover_responder_delete" qtlid="221656">Delete the auto-response</translation>
   <translation id="email_tab_popover_responder_update" qtlid="221669">Modify the auto-response</translation>
   <translation id="email_tab_modal_update_responder_title" qtlid="221682">Modify the auto-response</translation>
   <translation id="email_tab_modal_update_responder_heading" qtlid="221695">You are going to modify the auto-response {0}.</translation>
   <translation id="email_tab_modal_update_responder_info" qtlid="218562">Please enter the following information:</translation>
   <translation id="email_tab_modal_update_responder_success" qtlid="221708">The auto-response is being modified. The operation will take effect in 5 to 10 minutes.</translation>
   <translation id="email_tab_modal_update_responder_error" qtlid="221721">An error occurred when the auto-response was being modified.</translation>

   <translation id="email_tab_modal_help_title" qtlid="282731">Help with email configuration</translation>
   <translation id="email_tab_modal_help_explanation" qtlid="302119">You have just subscribed to an email hosting service. For help using this, please select one of the options below:</translation>
   <translation id="email_tab_modal_help_create_mailing_list" qtlid="219511">Add a mailing-list</translation>
   <translation id="email_tab_modal_help_explanation_checkbox_this" qtlid="282783">Do not show me this message again for this service. </translation>
   <translation id="email_tab_modal_help_explanation_checkbox_all" qtlid="282796">Do not show me this message again for all the other similar services. </translation>

   <translation id="email_tab_accounts_quota" qtlid="224802">Email account quota</translation>
   <translation id="email_tab_accounts_quota_info" qtlid="366696">You can create a postmaster email address for free to supplement your quota of available email addresses </translation>
   <translation id="email_tab_responders_quota" qtlid="224815">Automatic-reply quota</translation>
   <translation id="email_tab_redirections_quota" qtlid="224828">Redirection quota</translation>
   <translation id="email_tab_alias_quota" qtlid="224841">Alias quota</translation>
   <translation id="email_tab_domain_status" qtlid="19843">Service status </translation>
   <translation id="email_tab_domain_status_ok" qtlid="55133">Active</translation>
   <translation id="email_tab_domain_filer" qtlid="225902">Email filer</translation>
   <translation id="email_tab_domain_offer" qtlid="38217">Solution </translation>
   <translation id="email_tab_unavailable" qtlid="255508">The emails cannot be accessed</translation>
   <translation id="email_tab_domain_dns_filter" qtlid="273791">Antispam/Antivirus Filtering</translation>
   <translation id="email_tab_domain_dns_filter_edit" qtlid="272643">Edit the DNS filter  </translation>
   <translation id="email_tab_domain_dns_mx_records" qtlid="46780">MX fields</translation>
   <translation id="email_tab_domain_dns_filter_REDIRECT" qtlid="272656">Redirection only </translation>
   <translation id="email_tab_domain_dns_filter_NO_FILTERING" qtlid="273804">OVH without protection</translation>
   <translation id="email_tab_domain_dns_filter_SIMPLE_FILTERING" qtlid="273817">OVH Antispam</translation>
   <translation id="email_tab_domain_dns_filter_FULL_FILTERING" qtlid="273830">OVH Antispam/Antivirus</translation>
   <translation id="email_tab_domain_dns_filter_CUSTOM" qtlid="50062">Personalised</translation>
   <translation id="email_tab_domain_dns_filter_warning" qtlid="273886">Warning: This action will modify your MX servers so that they point to the selected OVH servers. </translation>

   <translation id="email_tab_popover_dns_filter_edit" qtlid="272643">Edit the DNS filter  </translation>
   <translation id="email_tab_popover_dns_filter_edit_info" qtlid="272695">Select the DNS filter that you wish to edit:</translation>
   <translation id="email_tab_domain_dns_filter_edit_custom" qtlid="272708">Customised filterv (server name,example: mx1.ovh.net)</translation>
   <translation id="emails_dns_filter_edit_success" qtlid="272721">The filter has been successfully modified.</translation>


   <translation id="email_tab_acl" qtlid="433693">Sharing administration for your emails</translation>
   <translation id="email_tab_acl_manage" qtlid="288769">Manage the elements shared by all email addresses </translation>
   <translation id="email_tab_acl_heading" qtlid="262804">Share the management of your emails</translation>
   <translation id="email_tab_acl_info" qtlid="262934">Here you are able to give someone rights to manage your mailbox, without allowing him or her access to the rest of your account. This person will have access to all your emails and must have an OVH user account.  </translation>
   <translation id="email_tab_table_acl_empty" qtlid="262830">No partner admin</translation>
   <translation id="email_tab_button_emails_add_acls" qtlid="262843">Add a username</translation>
   <translation id="email_tab_table_header_nic" qtlid="264420">OVH NIC-handle</translation>
   <translation id="email_tab_table_header_enter_nic" qtlid="265662">Enter your OVH NIC-handle </translation>
   <translation id="email_tab_table_acls_error" qtlid="243832">An error occurred when retrieving the details:</translation>

   <translation id="email_tab_table_acls_add_success" qtlid="262856">Username added.</translation>
   <translation id="email_tab_table_acls_add_error" qtlid="262869">An error occurred when adding a username:</translation>

   <translation id="email_tab_modal_delete_acl_title" qtlid="262882">Delete a username</translation>
   <translation id="email_tab_modal_delete_acl_heading" qtlid="262895">You are about to revoke the user rights <strong>{0}</strong>.</translation>

   <translation id="email_tab_modal_delete_acl_success" qtlid="262908">Username deleted.</translation>
   <translation id="email_tab_modal_delete_acl_error" qtlid="262921">An error occurred when deleting a username:</translation>

   <translation id="email_tab_modal_update_redirection_title" qtlid="269799">Modify a redirection</translation>
   <translation id="email_tab_modal_update_redirection_heading" qtlid="269812">You are about to modify this redirection</translation>
   <translation id="email_tab_modal_update_redirection_success" qtlid="269825">The redirection has been modified successfully. The operation will take effect in a few minutes. </translation>
   <translation id="email_tab_modal_update_redirection_error" qtlid="269838">An error occurred when modifying the redirection</translation>

   <translation id="email_tab_modal_migrate_title" qtlid="436619">Migrer le compte</translation>
   <translation id="email_tab_modal_migrate_account_email_label" qtlid="436671">E-mail source :</translation>
   <translation id="email_tab_modal_migrate_destination_service_label" qtlid="436697">Service de destination :</translation>
   <translation id="email_tab_modal_migrate_destination_service_help" qtlid="436710">Attention, vous ne pouvez migrer qu’un seul compte à la fois.</translation>
   <translation id="email_tab_modal_migrate_order_new_emails_button" qtlid="139169">Order accounts</translation>
   <translation id="email_tab_modal_migrate_available_email_selected" qtlid="436736">La migration de votre e-mail se fera sur le compte <strong>{0}</strong>.</translation>
   <translation id="email_tab_modal_migrate_remaining_available_emails" qtlid="436749">Après la migration, il vous restera <strong>{0}</strong> compte(s) libre(s).</translation>
   <translation id="email_tab_modal_migrate_no_remaining_available_emails" qtlid="436762">Après la migration, il ne vous restera plus de compte libre.</translation>
   <translation id="email_tab_modal_migrate_no_available_email" qtlid="436775">Vous n’avez plus de compte disponible sur votre service <strong>{0}</strong>. Choisissez un autre service dans la liste ou commandez un nouveau compte</translation>
   <translation id="email_tab_modal_migrate_order_email_service" qtlid="436788">Commander une solution e-mail</translation>
   <translation id="email_tab_modal_migrate_no_email_service" qtlid="436801">Vous n’avez pas de solution e-mail compatible pour la migration.</translation>
   <translation id="email_tab_modal_migrate_confirmation_delay" qtlid="436827">La migration du contenu peut prendre plusieurs heures selon la taille de la boite e-mail. Dès qu'elle sera terminée, votre boîte e-mail source sera supprimée dans un délai de 15 jours.</translation>
   <translation id="email_tab_modal_migrate_configuration_guides_button" qtlid="436866">Cliquez ici pour accéder à nos guides techniques</translation>
   <translation id="email_tab_modal_migrate_aknowledge" qtlid="436879">En validant, je reconnais avoir pris connaissance de toutes les informations concernant la migration du compte e-mail source sélectionné.</translation>
   <translation id="email_tab_modal_migrate_alert_configure_me" qtlid="436905">Il est nécessaire de disposer d’un compte e-mail non configuré (@configureme.me) pour réaliser l’opération.</translation>
   <translation id="email_tab_modal_migrate_alert_dont_change_password" qtlid="444404">Attention, veuillez ne pas modifier le mot de passe de votre compte tant que sa migration n'est pas terminée.</translation>
   <translation id="email_tab_modal_migrate_success" qtlid="436918">Votre compte e-mail est en cours de migration. L'opération sera effective d'ici 5 à 10 minutes.</translation>
   <translation id="email_tab_modal_migrate_error" qtlid="436931">Une erreur s'est produite lors de la migration du compte :</translation>

   <translation id="email_tab_TASK_table_empty" qtlid="144058">You don't have any tasks</translation>
   <translation id="email_tab_TASK_table_function" qtlid="61872">Task</translation>
   <translation id="email_tab_TASK_table_account" qtlid="33862">Account</translation>
   <translation id="email_tab_TASK_table_state" qtlid="26443">Status</translation>
   <translation id="email_tab_TASK_table_start_date" qtlid="26419">Creation date</translation>
   <translation id="email_tab_TASK_table_finish_date" qtlid="299897">End date </translation>
   <translation id="email_tab_TASK_warning" qtlid="108456">Warning!</translation>
   <translation id="email_tab_TASK_partial" qtlid="137426">The list displayed is incomplete, some tasks did not load correctly.</translation>
   <translation id="email_tab_TASK_error_message" qtlid="144097">An error occurred on loading the tasks.</translation>

   <translation id="email_tab_TASK_status_CANCELLED" qtlid="164623">Cancelled</translation>
   <translation id="email_tab_TASK_status_DOING" qtlid="26383">In progress</translation>
   <translation id="email_tab_TASK_status_DONE" qtlid="26395">Terminated</translation>
   <translation id="email_tab_TASK_status_ERROR" qtlid="45508">Error</translation>
   <translation id="email_tab_TASK_status_TODO" qtlid="197947">Planned</translation>
   <translation id="email_tab_TASK_status_INIT" qtlid="197960">Initiated</translation>

   <translation id="guide_emails_filter_subscope" qtlid="327211">Email filters </translation>
   <translation id="emails_configuration_guide_help" qtlid="273440">Do you need help configuring your email accounts?</translation>
   <translation id="emails_configuration_guide_outlook_help" qtlid="285382">Configuration with Microsoft Outlook 2013 video guide</translation>
   <translation id="emails_configuration_guide_ios_help" qtlid="285395">Configuration with iPhone IOS 9 video </translation>
   <translation id="guide_emails_responder_subscope" qtlid="50110">Voicemails</translation>
   <translation id="emails_guide_help" qtlid="156732">Read our online guides.</translation>
   <translation id="emails_guide_migration_exchange_help" qtlid="285095">For help with migrating an OVH email address to Exchange, <a href="{0}" target="_blank">view our guides</a></translation>
   <translation id="emails_guide_migration_ask_device" qtlid="402230">What sort of device are you going to install this email account on? </translation>

   <translation id="emails_configuration_guide_AUTO_help" qtlid="273319">Automatic configuration </translation>
   <translation id="emails_configuration_guide_MAC_help" qtlid="402243">Help for configuration on {0} Mac </translation>
   <translation id="emails_configuration_guide_OUTLOOK_help" qtlid="402256">Help for configuration on {0} Microsoft Outlook </translation>
   <translation id="emails_configuration_guide_IPHONE_help" qtlid="402269">Help for configuration on {0} iPhone </translation>
   <translation id="emails_configuration_guide_ANDROID_help" qtlid="402282">Help for configuration on {0} Android</translation>
   <translation id="emails_configuration_guide_OTHER_help" qtlid="402295">See all our guides </translation>

   <translation id="emails_configuration_guide_MAC_name" qtlid="402204">Mac</translation>
   <translation id="emails_configuration_guide_OUTLOOK_name" qtlid="24427">Outlook</translation>
   <translation id="emails_configuration_guide_IPHONE_name" qtlid="402308">iPhone</translation>
   <translation id="emails_configuration_guide_ANDROID_name" qtlid="402321">Android</translation>
   <translation id="emails_configuration_guide_OTHER_name" qtlid="19963">Other</translation>

   <translation id="emails_configuration_guide_icon_MAC_alt" qtlid="402334">Mac icon </translation>
   <translation id="emails_configuration_guide_icon_OUTLOOK_alt" qtlid="402347">Outlook icon </translation>
   <translation id="emails_configuration_guide_icon_IPHONE_alt" qtlid="402360">iPhone icon </translation>
   <translation id="emails_configuration_guide_icon_ANDROID_alt" qtlid="402373">Android icon </translation>
   <translation id="emails_configuration_guide_icon_OTHER_alt" qtlid="402386">OVH icon </translation>

   <translation id="email_tab_popover_delegate_title" qtlid="288782">Manage delegations </translation>
   <translation id="email_tab_popover_delegate_tab_header_name" qtlid="288795">NIC-handle with the delegation </translation>
   <translation id="email_tab_popover_delegate_tab_header_reload" qtlid="288808">Reload the list </translation>
   <translation id="email_tab_popover_delegate_tab_content_delete" qtlid="288821">Delete delegation </translation>
   <translation id="email_tab_popover_delegate_tab_content_add" qtlid="288834">Add a delegation </translation>
   <translation id="email_tab_popover_delegate_info" qtlid="288847">List of account delegations <strong>{0}</strong></translation>
   <translation id="email_tab_popover_delegate_format_error" qtlid="363839">NIC handle format not valid </translation>

   <translation id="emails_create_account" qtlid="58268">Create an account</translation>
   <translation id="emails_create_account_new_window" qtlid="211633">(New window)</translation>
</translations>
